odoo9_addon_report_custom_filename-9.0.1.0.0-py2.7-nspkg.pth
odoo9_addon_report_custom_filename-9.0.1.0.0.dist-info/top_level.txt
odoo9_addon_report_custom_filename-9.0.1.0.0.dist-info/WHEEL
odoo9_addon_report_custom_filename-9.0.1.0.0.dist-info/RECORD
odoo9_addon_report_custom_filename-9.0.1.0.0.dist-info/metadata.json
odoo9_addon_report_custom_filename-9.0.1.0.0.dist-info/DESCRIPTION.rst
odoo9_addon_report_custom_filename-9.0.1.0.0.dist-info/METADATA
odoo9_addon_report_custom_filename-9.0.1.0.0.dist-info/namespace_packages.txt
odoo_addons/report_custom_filename/__openerp__.py
odoo_addons/report_custom_filename/__init__.py
odoo_addons/report_custom_filename/README.rst
odoo_addons/report_custom_filename/view/ir_actions_report_xml.xml
odoo_addons/report_custom_filename/i18n/report_custom_filename.pot
odoo_addons/report_custom_filename/model/__init__.py
odoo_addons/report_custom_filename/model/ir_actions_report_xml.py
odoo_addons/report_custom_filename/controllers/reports.py
odoo_addons/report_custom_filename/controllers/report_controller.py
odoo_addons/report_custom_filename/controllers/__init__.py
odoo_addons/report_custom_filename/static/description/icon.png
